unienv-0.0.1b3.dist-info/licenses/LICENSE
unienv_data/__init__.py
unienv_data/base/__init__.py
unienv_data/base/common.py
unienv_data/base/storage.py
unienv_data/batches/__init__.py
unienv_data/batches/backend_compat.py
unienv_data/batches/combined_batch.py
unienv_data/batches/framestack_batch.py
unienv_data/batches/slicestack_batch.py
unienv_data/batches/transformations.py
unienv_data/integrations/pytorch.py
unienv_data/replay_buffer/__init__.py
unienv_data/replay_buffer/replay_buffer.py
unienv_data/replay_buffer/trajectory_replay_buffer.py
unienv_data/samplers/__init__.py
unienv_data/samplers/multiprocessing_sampler.py
unienv_data/samplers/step_sampler.py
unienv_data/storages/common.py
unienv_data/storages/hdf5.py
unienv_data/storages/pytorch.py
unienv_data/storages/transformation.py
unienv_data/transformations/image_compress.py
unienv_interface/__init__.py
unienv_interface/backends/__init__.py
unienv_interface/backends/base.py
unienv_interface/backends/jax.py
unienv_interface/backends/numpy.py
unienv_interface/backends/pytorch.py
unienv_interface/backends/serialization.py
unienv_interface/env_base/__init__.py
unienv_interface/env_base/env.py
unienv_interface/env_base/funcenv.py
unienv_interface/env_base/funcenv_wrapper.py
unienv_interface/env_base/vec_env.py
unienv_interface/env_base/wrapper.py
unienv_interface/func_wrapper/__init__.py
unienv_interface/func_wrapper/frame_stack.py
unienv_interface/func_wrapper/transformation.py
unienv_interface/space/__init__.py
unienv_interface/space/space.py
unienv_interface/space/space_utils/__init__.py
unienv_interface/space/space_utils/batch_utils.py
unienv_interface/space/space_utils/construct_utils.py
unienv_interface/space/space_utils/flatten_utils.py
unienv_interface/space/space_utils/gym_utils.py
unienv_interface/space/space_utils/serialization_utils.py
unienv_interface/space/spaces/__init__.py
unienv_interface/space/spaces/batched.py
unienv_interface/space/spaces/binary.py
unienv_interface/space/spaces/box.py
unienv_interface/space/spaces/dict.py
unienv-0.0.1b3.dist-info/METADATA
unienv-0.0.1b3.dist-info/WHEEL
unienv-0.0.1b3.dist-info/top_level.txt
unienv-0.0.1b3.dist-info/RECORD
