Metadata-Version: 2.4
Name: unienv
Version: 0.0.1b3
Summary: Unified robot environment framework supporting multiple tensor and simulation backends
License-Expression: MIT
Project-URL: Homepage, https://github.com/UniEnvOrg/UniEnv
Project-URL: Documentation, https://github.com/UniEnvOrg/UniEnv
Project-URL: Repository, https://github.com/UniEnvOrg/UniEnv
Project-URL: Issues, https://github.com/UniEnvOrg/UniEnv/issues
Project-URL: Changelog, https://github.com/UniEnvOrg/UniEnv/blob/main/CHANGELOG.md
Requires-Python: >=3.10
License-File: LICENSE
Requires-Dist: numpy
Requires-Dist: xbarray>=0.0.1a8
Requires-Dist: pillow
Requires-Dist: cloudpickle
Provides-Extra: dev
Requires-Dist: pytest; extra == "dev"
Provides-Extra: gymnasium
Requires-Dist: gymnasium>=0.29.0; extra == "gymnasium"
Provides-Extra: video
Requires-Dist: moviepy>=2.1; extra == "video"
Dynamic: license-file
